{
   "agent": "Crossbar.io",
   "behavior": "OK",
   "behaviorClose": "OK",
   "case": 130,
   "closedByMe": false,
   "createStats": true,
   "createWirelog": true,
   "description": "Send a text message with payload which is not valid UTF-8 in one fragment.<br><br>Payload: 0xdf",
   "droppedByMe": false,
   "duration": 2,
   "expectation": "The connection is failed immediately, since the payload is not valid UTF-8.",
   "expected": {
      "OK": []
   },
   "expectedClose": {
      "closeCode": [
         1007
      ],
      "closedByMe": false,
      "closedByWrongEndpointIsFatal": true,
      "requireClean": false
   },
   "failedByMe": false,
   "httpRequest": "GET / HTTP/1.1\r\nUser-Agent: AutobahnTestSuite/0.7.2-0.10.9\r\nHost: 127.0.0.1:8080\r\nUpgrade: WebSocket\r\nConnection: Upgrade\r\nPragma: no-cache\r\nCache-Control: no-cache\r\nSec-WebSocket-Key: 1wdix6Elcdv0Ft8gRZUHXg==\r\nSec-WebSocket-Version: 13\r\n\r\n",
   "httpResponse": "HTTP/1.1 101 Switching Protocols\r\nServer: Crossbar/0.11.1\r\nX-Powered-By: AutobahnPython/0.11.0\r\nUpgrade: WebSocket\r\nConnection: Upgrade\r\nSec-WebSocket-Accept: fZnplWK9Qi7tFslvHVEcEfhJNlc=\r\n\r\n",
   "id": "6.14.6",
   "isServer": false,
   "localCloseCode": 1000,
   "localCloseReason": null,
   "received": [],
   "remoteCloseCode": 1007,
   "remoteCloseReason": "UTF-8 text message payload ended within Unicode code point at payload octet index 1",
   "reportCompressionRatio": false,
   "reportTime": false,
   "result": "Actual events match at least one expected.",
   "resultClose": "Connection was properly closed",
   "rxFrameStats": {
      "8": 1
   },
   "rxOctetStats": {
      "87": 1,
      "191": 1
   },
   "started": "2015-11-06T15:56:10.363Z",
   "trafficStats": null,
   "txFrameStats": {
      "1": 1,
      "8": 1
   },
   "txOctetStats": {
      "7": 1,
      "8": 1,
      "240": 1
   },
   "wasClean": true,
   "wasCloseHandshakeTimeout": false,
   "wasNotCleanReason": null,
   "wasOpenHandshakeTimeout": false,
   "wasServerConnectionDropTimeout": false,
   "wirelog": [
      [
         "TO",
         [
            240,
            "474554202f20485454502f312e310d0a557365722d4167656e743a204175746f6261686e5465737453756974652f302e372e322d302e31302e390d0a486f7374 ..."
         ],
         false
      ],
      [
         "RO",
         [
            191,
            "485454502f312e312031303120537769746368696e672050726f746f636f6c730d0a5365727665723a2043726f73736261722f302e31312e310d0a582d506f77 ..."
         ]
      ],
      [
         "TF",
         [
            1,
            "0xdf"
         ],
         1,
         true,
         0,
         "96292963",
         null,
         null,
         false
      ],
      [
         "TO",
         [
            7,
            "81819629296349"
         ],
         false
      ],
      [
         "KL",
         0.5
      ],
      [
         "RO",
         [
            87,
            "885503ef5554462d382074657874206d657373616765207061796c6f616420656e6465642077697468696e20556e69636f646520636f646520706f696e742061 ..."
         ]
      ],
      [
         "RF",
         [
            85,
            "0x03ef5554462d382074657874206d657373616765207061796c6f616420656e6465642077697468696e20556e69636f646520636f646520706f696e7420617420 ..."
         ],
         8,
         true,
         0,
         false,
         null
      ],
      [
         "TF",
         [
            2,
            "0x03e8"
         ],
         8,
         true,
         0,
         "e8a75661",
         null,
         null,
         false
      ],
      [
         "TO",
         [
            8,
            "8882e8a75661eb4f"
         ],
         false
      ]
   ]
}